flask_vue_sfc/__init__.py
flask_vue_sfc/helpers.py
flask_vue_sfc/utils.py
flask_vue_sfc/static/js/escodegen.js
flask_vue_sfc/static/js/vue-template-compiler.js
flask_vue_sfc/static/js/vue.js
flask_vue_sfc/static/js/vue.min.js
flask_vue_sfc/templates/page.html
Flask_Vue_SFC-0.0.3.dist-info/METADATA
Flask_Vue_SFC-0.0.3.dist-info/WHEEL
Flask_Vue_SFC-0.0.3.dist-info/top_level.txt
Flask_Vue_SFC-0.0.3.dist-info/RECORD
