Metadata-Version: 2.1
Name: Flask-Vue-SFC
Version: 0.0.3
Summary: Flask extension for rendering Vue.js SFCs
Home-page: https://github.com/michaelbukachi/flask_vue_sfc
Author: Michael Bukachi
Author-email: michaelbukachi@gmail.com
License: Apache
Platform: any
Classifier: Development Status :: 4 - Beta
Classifier: Environment :: Web Environment
Classifier: Framework :: Flask
Classifier: Intended Audience :: Developers
Classifier: License :: OSI Approved :: Apache Software License
Classifier: Operating System :: OS Independent
Classifier: Programming Language :: Python
Classifier: Programming Language :: Python :: 3
Classifier: Programming Language :: Python :: 3.4
Classifier: Programming Language :: Python :: 3.5
Classifier: Programming Language :: Python :: 3.6
Classifier: Programming Language :: Python :: 3.7
Classifier: Programming Language :: Python :: 3.8
Classifier: Topic :: Internet :: WWW/HTTP :: Dynamic Content
Classifier: Topic :: Software Development :: Libraries :: Python Modules
Requires-Python: >=3.4
Requires-Dist: Flask (>=0.11)
Requires-Dist: py-mini-racer (>=0.4.0)
Requires-Dist: tinycss2 (>=1.0.2)
Requires-Dist: esprima (>=4.0.1)
Requires-Dist: css-html-js-minify
